{
  "version": "1.0",
  "paths": {
    "base_sync_dir": "C:\\FTS_SYNC",
    "add_to_central_script": "add_to_database_central.py",
    "logs_folder_name": "logs"
  },
  "retention": {
    "enabled": true,
    "days": 7,
    "folder_prefix": "Database_",
    "date_format": "ddMMyy"
  },
  "ssh": {
    "user": "localfts",
    "batch_mode": true,
    "connect_timeout_seconds": 20,
    "remote_command": "cd C:\\Users\\localfts\\desktop\\endform_display && .\\venv\\Scripts\\python.exe utilities/export_remote_db.py"
  },
  "postgres": {
    "docker_container": "postgres-fts",
    "database": "postgres",
    "user": "postgres",
    "target_table": "model_results_central",
    "source_station_column": "source_station"
  },
  "stations": [
    {
      "enabled": true,
      "name": "ART_ENDFORM_1859_RIGHT",
      "ip": "10.208.12.150",
      "output_file": "1859_RIGHT_DB.sql"
    },
    {
      "enabled": true,
      "name": "ART_ENDFORM_1859_LEFT",
      "ip": "10.208.12.132",
      "output_file": "1859_LEFT_DB.sql"
    },
    {
      "enabled": true,
      "name": "ART_ENDFORM_1861_RIGHT",
      "ip": "10.208.12.109",
      "output_file": "1861_RIGHT_DB.sql"
    },
    {
      "enabled": true,
      "name": "ART_ENDFORM_1861_LEFT",
      "ip": "10.208.12.148",
      "output_file": "1861_LEFT_DB.sql"
    },
    {
      "enabled": true,
      "name": "ART_ENDFORM_1862_RIGHT",
      "ip": "10.208.12.75",
      "output_file": "1862_RIGHT_DB.sql"
    },
    {
      "enabled": true,
      "name": "ART_ENDFORM_1862_LEFT",
      "ip": "10.208.12.76",
      "output_file": "1862_LEFT_DB.sql"
    }
  ]
}